{
  "posts": [
    {
      "id": 1,
      "title": "Hunchback of Notre Dame, The",
      "description": "Aliquam quis turpis eget elit sodales scelerisque. Mauris sit amet eros. Suspendisse accumsan tortor quis turpis."
    },
    {
      "id": 2,
      "title": "Butterfly (La lengua de las mariposas)",
      "description": "Fusce posuere felis sed lacus. Morbi sem mauris, laoreet ut, rhoncus aliquet, pulvinar sed, nisl. Nunc rhoncus dui vel sem."
    },
    {
      "id": 3,
      "title": "633 Squadron",
      "description": "Nullam porttitor lacus at turpis. Donec posuere metus vitae ipsum. Aliquam non mauris."
    },
    {
      "id": 4,
      "title": "Phantom of the Opera, The",
      "description": "Duis bibendum. Morbi non quam nec dui luctus rutrum. Nulla tellus."
    },
    {
      "id": 5,
      "title": "Purge, The",
      "description": "Integer ac leo. Pellentesque ultrices mattis odio. Donec vitae nisi.\n\nNam ultrices, libero non mattis pulvinar, nulla pede ullamcorper augue, a suscipit nulla elit ac nulla. Sed vel enim sit amet nunc viverra dapibus. Nulla suscipit ligula in lacus."
    }
  ]
}